devpk-0.2.1.dist-info/METADATA
devpk-0.2.1.dist-info/WHEEL
devpk-0.2.1.dist-info/entry_points.txt
devpk/__init__.py
devpk-0.2.1.dist-info/RECORD
